setup.py
tor_access/__init__.py
tor_access.egg-info/PKG-INFO
tor_access.egg-info/SOURCES.txt
tor_access.egg-info/dependency_links.txt
tor_access.egg-info/requires.txt
tor_access.egg-info/top_level.txt