Metadata-Version: 1.0
Name: tor-access
Version: 0.1.dev
Summary: User role access for tornado
Home-page: http://github.com/comger/tor_access
Author: comger@gmail.com
Author-email: comger@gmail.com
License: https://github.com/comger/tor_access/blob/master/LICENSE
Keywords: url access,role,tornado
Platform: UNKNOWN
Classifier: License :: OSI Approved :: Apache Software License
Classifier: Programming Language :: Python :: 2
Classifier: Programming Language :: Python :: 2.6
Classifier: Programming Language :: Python :: 2.7
Classifier: Programming Language :: Python :: Implementation :: CPython
Classifier: Programming Language :: Python :: Implementation :: PyPy
